MANIFEST.in
setup.py
Products/__init__.py
Products.PloneHotfix20150910.egg-info/PKG-INFO
Products.PloneHotfix20150910.egg-info/SOURCES.txt
Products.PloneHotfix20150910.egg-info/dependency_links.txt
Products.PloneHotfix20150910.egg-info/entry_points.txt
Products.PloneHotfix20150910.egg-info/namespace_packages.txt
Products.PloneHotfix20150910.egg-info/not-zip-safe
Products.PloneHotfix20150910.egg-info/requires.txt
Products.PloneHotfix20150910.egg-info/top_level.txt
Products/PloneHotfix20150910/README.txt
Products/PloneHotfix20150910/__init__.py
Products/PloneHotfix20150910/addMember.py
Products/PloneHotfix20150910/isURLInPortal.py
Products/PloneHotfix20150910/kupu.py
Products/PloneHotfix20150910/setHeader.py
docs/HISTORY.txt
docs/INSTALL.txt
docs/LICENSE.GPL
docs/LICENSE.txt