Metadata-Version: 1.1
Name: Products.PloneHotfix20150910
Version: 1.1
Summary: Various Plone hotfixes, 2015-09-10
Home-page: http://github.com/plone
Author: Plone Security Team
Author-email: security@plone.org
License: GPL
Keywords: plone security hotfix patch
Platform: UNKNOWN
Classifier: Framework :: Plone
Classifier: Programming Language :: Python
